vault_dec/__init__.py
vault_dec/__main__.py
vault_dec-0.1.3.dist-info/LICENSE.md
vault_dec-0.1.3.dist-info/METADATA
vault_dec-0.1.3.dist-info/WHEEL
vault_dec-0.1.3.dist-info/top_level.txt
vault_dec-0.1.3.dist-info/RECORD
