Metadata-Version: 2.1
Name: vault-dec
Version: 0.1.3
Summary: Vault Decrypt
Author: Aleksey Leontiev
Author-email: alekseyl@list.ru
License: MIT
Classifier: Intended Audience :: Developers
Classifier: License :: Free for non-commercial use
Classifier: Programming Language :: Python :: 3 :: Only
Classifier: Programming Language :: Python :: 3.8
Classifier: Programming Language :: Python :: 3.9
Classifier: Programming Language :: Python :: 3.10
License-File: LICENSE.md
Requires-Dist: hvac (==0.11.*)
Requires-Dist: ConfigArgParse (==1.5.*)
